{
    "total_count": 70,
    "incomplete_results": false,
    "items": [
              {
              "id": 1577063,
              "name": "GithubBrowser",
              "full_name": "oscardelben/GithubBrowser",
              "owner": {
              "login": "oscardelben",
              "id": 3892,
              "avatar_url": "https://avatars2.githubusercontent.com/u/3892?v=3",
              "gravatar_id": "",
              "url": "https://api.github.com/users/oscardelben",
              "html_url": "https://github.com/oscardelben",
              "followers_url": "https://api.github.com/users/oscardelben/followers",
              "following_url": "https://api.github.com/users/oscardelben/following{/other_user}",
              "gists_url": "https://api.github.com/users/oscardelben/gists{/gist_id}",
              "starred_url": "https://api.github.com/users/oscardelben/starred{/owner}{/repo}",
              "subscriptions_url": "https://api.github.com/users/oscardelben/subscriptions",
              "organizations_url": "https://api.github.com/users/oscardelben/orgs",
              "repos_url": "https://api.github.com/users/oscardelben/repos",
              "events_url": "https://api.github.com/users/oscardelben/events{/privacy}",
              "received_events_url": "https://api.github.com/users/oscardelben/received_events",
              "type": "User",
              "site_admin": false
              },
              "private": false,
              "html_url": "https://github.com/oscardelben/GithubBrowser",
              "description": "A Github Browser For iPad",
              "fork": false,
              "url": "https://api.github.com/repos/oscardelben/GithubBrowser",
              "forks_url": "https://api.github.com/repos/oscardelben/GithubBrowser/forks",
              "keys_url": "https://api.github.com/repos/oscardelben/GithubBrowser/keys{/key_id}",
              "collaborators_url": "https://api.github.com/repos/oscardelben/GithubBrowser/collaborators{/collaborator}",
              "teams_url": "https://api.github.com/repos/oscardelben/GithubBrowser/teams",
              "hooks_url": "https://api.github.com/repos/oscardelben/GithubBrowser/hooks",
              "issue_events_url": "https://api.github.com/repos/oscardelben/GithubBrowser/issues/events{/number}",
              "events_url": "https://api.github.com/repos/oscardelben/GithubBrowser/events",
              "assignees_url": "https://api.github.com/repos/oscardelben/GithubBrowser/assignees{/user}",
              "branches_url": "https://api.github.com/repos/oscardelben/GithubBrowser/branches{/branch}",
              "tags_url": "https://api.github.com/repos/oscardelben/GithubBrowser/tags",
              "blobs_url": "https://api.github.com/repos/oscardelben/GithubBrowser/git/blobs{/sha}",
              "git_tags_url": "https://api.github.com/repos/oscardelben/GithubBrowser/git/tags{/sha}",
              "git_refs_url": "https://api.github.com/repos/oscardelben/GithubBrowser/git/refs{/sha}",
              "trees_url": "https://api.github.com/repos/oscardelben/GithubBrowser/git/trees{/sha}",
              "statuses_url": "https://api.github.com/repos/oscardelben/GithubBrowser/statuses/{sha}",
              "languages_url": "https://api.github.com/repos/oscardelben/GithubBrowser/languages",
              "stargazers_url": "https://api.github.com/repos/oscardelben/GithubBrowser/stargazers",
              "contributors_url": "https://api.github.com/repos/oscardelben/GithubBrowser/contributors",
              "subscribers_url": "https://api.github.com/repos/oscardelben/GithubBrowser/subscribers",
              "subscription_url": "https://api.github.com/repos/oscardelben/GithubBrowser/subscription",
              "commits_url": "https://api.github.com/repos/oscardelben/GithubBrowser/commits{/sha}",
              "git_commits_url": "https://api.github.com/repos/oscardelben/GithubBrowser/git/commits{/sha}",
              "comments_url": "https://api.github.com/repos/oscardelben/GithubBrowser/comments{/number}",
              "issue_comment_url": "https://api.github.com/repos/oscardelben/GithubBrowser/issues/comments{/number}",
              "contents_url": "https://api.github.com/repos/oscardelben/GithubBrowser/contents/{+path}",
              "compare_url": "https://api.github.com/repos/oscardelben/GithubBrowser/compare/{base}...{head}",
              "merges_url": "https://api.github.com/repos/oscardelben/GithubBrowser/merges",
              "archive_url": "https://api.github.com/repos/oscardelben/GithubBrowser/{archive_format}{/ref}",
              "downloads_url": "https://api.github.com/repos/oscardelben/GithubBrowser/downloads",
              "issues_url": "https://api.github.com/repos/oscardelben/GithubBrowser/issues{/number}",
              "pulls_url": "https://api.github.com/repos/oscardelben/GithubBrowser/pulls{/number}",
              "milestones_url": "https://api.github.com/repos/oscardelben/GithubBrowser/milestones{/number}",
              "notifications_url": "https://api.github.com/repos/oscardelben/GithubBrowser/notifications{?since,all,participating}",
              "labels_url": "https://api.github.com/repos/oscardelben/GithubBrowser/labels{/name}",
              "releases_url": "https://api.github.com/repos/oscardelben/GithubBrowser/releases{/id}",
              "deployments_url": "https://api.github.com/repos/oscardelben/GithubBrowser/deployments",
              "created_at": "2011-04-06T12:49:17Z",
              "updated_at": "2013-10-22T13:45:37Z",
              "pushed_at": "2011-10-05T08:45:56Z",
              "git_url": "git://github.com/oscardelben/GithubBrowser.git",
              "ssh_url": "git@github.com:oscardelben/GithubBrowser.git",
              "clone_url": "https://github.com/oscardelben/GithubBrowser.git",
              "svn_url": "https://github.com/oscardelben/GithubBrowser",
              "homepage": "",
              "size": 1392,
              "stargazers_count": 28,
              "watchers_count": 28,
              "language": "Objective-C",
              "has_issues": true,
              "has_projects": true,
              "has_downloads": true,
              "has_wiki": true,
              "has_pages": false,
              "forks_count": 4,
              "mirror_url": null,
              "open_issues_count": 0,
              "forks": 4,
              "open_issues": 0,
              "watchers": 28,
              "default_branch": "master",
              "score": 55.659855
              },
              {
              "id": 49380528,
              "name": "GitHubBrowserExample",
              "full_name": "ReSwift/GitHubBrowserExample",
              "owner": {
              "login": "ReSwift",
              "id": 16023071,
              "avatar_url": "https://avatars2.githubusercontent.com/u/16023071?v=3",
              "gravatar_id": "",
              "url": "https://api.github.com/users/ReSwift",
              "html_url": "https://github.com/ReSwift",
              "followers_url": "https://api.github.com/users/ReSwift/followers",
              "following_url": "https://api.github.com/users/ReSwift/following{/other_user}",
              "gists_url": "https://api.github.com/users/ReSwift/gists{/gist_id}",
              "starred_url": "https://api.github.com/users/ReSwift/starred{/owner}{/repo}",
              "subscriptions_url": "https://api.github.com/users/ReSwift/subscriptions",
              "organizations_url": "https://api.github.com/users/ReSwift/orgs",
              "repos_url": "https://api.github.com/users/ReSwift/repos",
              "events_url": "https://api.github.com/users/ReSwift/events{/privacy}",
              "received_events_url": "https://api.github.com/users/ReSwift/received_events",
              "type": "Organization",
              "site_admin": false
              },
              "private": false,
              "html_url": "https://github.com/ReSwift/GitHubBrowserExample",
              "description": "[WIP] Real World Example for ReSwift",
              "fork": false,
              "url": "https://api.github.com/repos/ReSwift/GitHubBrowserExample",
              "forks_url": "https://api.github.com/repos/ReSwift/GitHubBrowserExample/forks",
              "keys_url": "https://api.github.com/repos/ReSwift/GitHubBrowserExample/keys{/key_id}",
              "collaborators_url": "https://api.github.com/repos/ReSwift/GitHubBrowserExample/collaborators{/collaborator}",
              "teams_url": "https://api.github.com/repos/ReSwift/GitHubBrowserExample/teams",
              "hooks_url": "https://api.github.com/repos/ReSwift/GitHubBrowserExample/hooks",
              "issue_events_url": "https://api.github.com/repos/ReSwift/GitHubBrowserExample/issues/events{/number}",
              "events_url": "https://api.github.com/repos/ReSwift/GitHubBrowserExample/events",
              "assignees_url": "https://api.github.com/repos/ReSwift/GitHubBrowserExample/assignees{/user}",
              "branches_url": "https://api.github.com/repos/ReSwift/GitHubBrowserExample/branches{/branch}",
              "tags_url": "https://api.github.com/repos/ReSwift/GitHubBrowserExample/tags",
              "blobs_url": "https://api.github.com/repos/ReSwift/GitHubBrowserExample/git/blobs{/sha}",
              "git_tags_url": "https://api.github.com/repos/ReSwift/GitHubBrowserExample/git/tags{/sha}",
              "git_refs_url": "https://api.github.com/repos/ReSwift/GitHubBrowserExample/git/refs{/sha}",
              "trees_url": "https://api.github.com/repos/ReSwift/GitHubBrowserExample/git/trees{/sha}",
              "statuses_url": "https://api.github.com/repos/ReSwift/GitHubBrowserExample/statuses/{sha}",
              "languages_url": "https://api.github.com/repos/ReSwift/GitHubBrowserExample/languages",
              "stargazers_url": "https://api.github.com/repos/ReSwift/GitHubBrowserExample/stargazers",
              "contributors_url": "https://api.github.com/repos/ReSwift/GitHubBrowserExample/contributors",
              "subscribers_url": "https://api.github.com/repos/ReSwift/GitHubBrowserExample/subscribers",
              "subscription_url": "https://api.github.com/repos/ReSwift/GitHubBrowserExample/subscription",
              "commits_url": "https://api.github.com/repos/ReSwift/GitHubBrowserExample/commits{/sha}",
              "git_commits_url": "https://api.github.com/repos/ReSwift/GitHubBrowserExample/git/commits{/sha}",
              "comments_url": "https://api.github.com/repos/ReSwift/GitHubBrowserExample/comments{/number}",
              "issue_comment_url": "https://api.github.com/repos/ReSwift/GitHubBrowserExample/issues/comments{/number}",
              "contents_url": "https://api.github.com/repos/ReSwift/GitHubBrowserExample/contents/{+path}",
              "compare_url": "https://api.github.com/repos/ReSwift/GitHubBrowserExample/compare/{base}...{head}",
              "merges_url": "https://api.github.com/repos/ReSwift/GitHubBrowserExample/merges",
              "archive_url": "https://api.github.com/repos/ReSwift/GitHubBrowserExample/{archive_format}{/ref}",
              "downloads_url": "https://api.github.com/repos/ReSwift/GitHubBrowserExample/downloads",
              "issues_url": "https://api.github.com/repos/ReSwift/GitHubBrowserExample/issues{/number}",
              "pulls_url": "https://api.github.com/repos/ReSwift/GitHubBrowserExample/pulls{/number}",
              "milestones_url": "https://api.github.com/repos/ReSwift/GitHubBrowserExample/milestones{/number}",
              "notifications_url": "https://api.github.com/repos/ReSwift/GitHubBrowserExample/notifications{?since,all,participating}",
              "labels_url": "https://api.github.com/repos/ReSwift/GitHubBrowserExample/labels{/name}",
              "releases_url": "https://api.github.com/repos/ReSwift/GitHubBrowserExample/releases{/id}",
              "deployments_url": "https://api.github.com/repos/ReSwift/GitHubBrowserExample/deployments",
              "created_at": "2016-01-10T18:55:16Z",
              "updated_at": "2017-04-14T06:03:58Z",
              "pushed_at": "2016-12-19T13:19:44Z",
              "git_url": "git://github.com/ReSwift/GitHubBrowserExample.git",
              "ssh_url": "git@github.com:ReSwift/GitHubBrowserExample.git",
              "clone_url": "https://github.com/ReSwift/GitHubBrowserExample.git",
              "svn_url": "https://github.com/ReSwift/GitHubBrowserExample",
              "homepage": "",
              "size": 5342,
              "stargazers_count": 49,
              "watchers_count": 49,
              "language": "Swift",
              "has_issues": true,
              "has_projects": true,
              "has_downloads": true,
              "has_wiki": true,
              "has_pages": false,
              "forks_count": 12,
              "mirror_url": null,
              "open_issues_count": 0,
              "forks": 12,
              "open_issues": 0,
              "watchers": 49,
              "default_branch": "master",
              "score": 23.694187
              }
              ]
}
